pytest_django_rq/__init__.py
pytest_django_rq/django_rq_worker.py
pytest_django_rq/utils.py
pytest_django_rq/version.py
pytest_django_rq-0.2.0.dist-info/METADATA
pytest_django_rq-0.2.0.dist-info/WHEEL
pytest_django_rq-0.2.0.dist-info/entry_points.txt
pytest_django_rq-0.2.0.dist-info/top_level.txt
pytest_django_rq-0.2.0.dist-info/RECORD
