Metadata-Version: 2.1
Name: pytest-django-rq
Version: 0.2.0
Summary: A pytest plugin to help writing unit test for django-rq
Home-page: https://github.com/ein-plus/pytest-django-rq
Author: Qiangning Hong
Author-email: hongqn@ein.plus
License: MIT
Platform: UNKNOWN
Classifier: Development Status :: 4 - Beta
Classifier: Framework :: Django
Classifier: Framework :: Pytest
Classifier: Intended Audience :: Developers
Classifier: License :: OSI Approved :: MIT License
Classifier: Operating System :: OS Independent
Classifier: Programming Language :: Python :: 3
Classifier: Programming Language :: Python :: 3 :: Only
Classifier: Programming Language :: Python :: 3.6
Classifier: Programming Language :: Python :: 3.7
Classifier: Programming Language :: Python :: 3.8
Requires-Python: >=3.6
Requires-Dist: pytest-mock
Requires-Dist: fakeredis
